pywxbase/__init__.pyc
pywxbase/config/logger.json
pywxbase/helper/__init__.pyc
pywxbase/helper/__init__.pyi
pywxbase/helper/wx_devices.pyc
pywxbase/helper/wx_devices.pyi
pywxbase/helper/wx_files.pyc
pywxbase/helper/wx_files.pyi
pywxbase/helper/wx_paths.pyc
pywxbase/helper/wx_paths.pyi
pywxbase/helper/wx_singletons.pyc
pywxbase/helper/wx_singletons.pyi
pywxbase/helper/wx_strings.pyc
pywxbase/helper/wx_strings.pyi
pywxbase/helper/wx_times.pyc
pywxbase/helper/wx_times.pyi
pywxbase/logger/__init__.pyc
pywxbase/logger/__init__.pyi
pywxbase/logger/wx_logger.pyc
pywxbase/logger/wx_logger.pyi
pywxbase/message/__init__.pyc
pywxbase/message/__init__.pyi
pywxbase/message/wx_event.pyc
pywxbase/message/wx_event.pyi
pywxbase/thread/__init__.pyc
pywxbase/thread/__init__.pyi
pywxbase/thread/wx_handler.pyc
pywxbase/thread/wx_handler.pyi
pywxbase-1.1.0.dist-info/METADATA
pywxbase-1.1.0.dist-info/WHEEL
pywxbase-1.1.0.dist-info/top_level.txt
pywxbase-1.1.0.dist-info/RECORD
